adafruit_lis3mdl.py
adafruit_circuitpython_lis3mdl-1.2.5.dist-info/licenses/LICENSE
adafruit_circuitpython_lis3mdl-1.2.5.dist-info/METADATA
adafruit_circuitpython_lis3mdl-1.2.5.dist-info/WHEEL
adafruit_circuitpython_lis3mdl-1.2.5.dist-info/top_level.txt
adafruit_circuitpython_lis3mdl-1.2.5.dist-info/RECORD
